Metadata-Version: 1.1
Name: multyvac
Version: 0.4.9
Summary: Multyvac for Python
Home-page: http://www.multyvac.com
Author: Multyvac, Inc.
Author-email: dev@multyvac.com
License: LICENSE.txt
Platform: CPython 2.6
Platform: CPython 2.7
Classifier: Development Status :: 4 - Beta
Classifier: Intended Audience :: Developers
Classifier: License :: OSI Approved :: BSD License
Classifier: Operating System :: POSIX
Classifier: Operating System :: Microsoft :: Windows
Classifier: Operating System :: MacOS :: MacOS X
Classifier: Programming Language :: Python :: 2.6
Classifier: Programming Language :: Python :: 2.7
Classifier: Topic :: Software Development :: Libraries :: Python Modules
Classifier: Topic :: Scientific/Engineering
Classifier: Topic :: System :: Distributed Computing
